cpy/__init__.py
cpy/dicts/__init__.py
cpy/dicts/tree.py
cpy/lists/__init__.py
cpy/lists/dict_list.py
cpy/lists/iteration.py
cpy/lists/redis_list.py
cpy/timer/__init__.py
cpy/timer/chkt.py
cpy-1.0.5.dist-info/METADATA
cpy-1.0.5.dist-info/WHEEL
cpy-1.0.5.dist-info/top_level.txt
cpy-1.0.5.dist-info/RECORD
