Metadata-Version: 2.1
Name: cpy
Version: 1.0.5
Summary: Charzeh Python Helpers
Home-page: https://github.com/amirmd76/cpy.git
Author: Amir Dehghan
Author-email: dehghan@mit.edu
License: MIT
Platform: UNKNOWN
